{"cameraMode":{"drawMode":0,"name":"Shaded","section":"Shading Mode"},"sceneLighting":true,"audioPlay":false,"sceneViewState":{"showFog":true,"showMaterialUpdate":false,"showSkybox":true,"showFlares":true,"showImageEffects":true,"showParticleSystems":true},"in2DMode":false,"pivot":{"x":336.0881652832031,"y":38.136146545410159,"z":84.47221374511719},"rotation":{"x":0.0392521433532238,"y":0.6803507804870606,"z":-0.03706821799278259,"w":0.7311615347862244},"size":7.620846271514893,"orthographic":false}